webez/__init__.py
webez/cli.py
webez/css_converter.py
webez/html_converter.py
webez-0.1.0.dist-info/METADATA
webez-0.1.0.dist-info/WHEEL
webez-0.1.0.dist-info/entry_points.txt
webez-0.1.0.dist-info/top_level.txt
webez-0.1.0.dist-info/RECORD
